ya_activity/__init__.py
ya_activity/__init__.py.orig
ya_activity/__init__.py.rej
ya_activity/api/__init__.py
ya_activity/api/provider_api.py
ya_activity/api/provider_api.py.orig
ya_activity/api/provider_api.py.rej
ya_activity/api/requestor_control_api.py
ya_activity/api/requestor_control_api.py.orig
ya_activity/api/requestor_control_api.py.rej
ya_activity/api/requestor_state_api.py
ya_activity/api/requestor_state_api.py.orig
ya_activity/api/requestor_state_api.py.rej
ya_activity/api_client.py
ya_activity/configuration.py
ya_activity/configuration.py.orig
ya_activity/configuration.py.rej
ya_activity/configuration.pyi
ya_activity/exceptions.py
ya_activity/models/__init__.py
ya_activity/models/__init__.pyi
ya_activity/models/activity_state.py
ya_activity/models/activity_usage.py
ya_activity/models/activity_usage.py.orig
ya_activity/models/command_output_bin.py
ya_activity/models/command_output_bin_all_of.py
ya_activity/models/command_output_str.py
ya_activity/models/command_output_str_all_of.py
ya_activity/models/create_activity.py
ya_activity/models/create_activity.py.orig
ya_activity/models/create_activity.py.rej
ya_activity/models/create_activity_all_of.py
ya_activity/models/create_activity_all_of.py.orig
ya_activity/models/create_activity_all_of.py.rej
ya_activity/models/create_activity_request.py
ya_activity/models/create_activity_result.py
ya_activity/models/credentials.py
ya_activity/models/deploy_command.py
ya_activity/models/deploy_command_all_of.py
ya_activity/models/deploy_command_body.py
ya_activity/models/deploy_network.py
ya_activity/models/destroy_activity.py
ya_activity/models/destroy_activity.py.orig
ya_activity/models/destroy_activity.py.rej
ya_activity/models/error_message.py
ya_activity/models/exe_script_command_result.py
ya_activity/models/exe_script_command_result.py.orig
ya_activity/models/exe_script_command_result.py.rej
ya_activity/models/exe_script_command_state.py
ya_activity/models/exe_script_command_state.py.orig
ya_aioclient-0.6.4.dist-info/WHEEL
ya_aioclient-0.6.4.dist-info/METADATA
ya_aioclient-0.6.4.dist-info/RECORD
