Metadata-Version: 2.1
Name: ya-aioclient
Version: 0.6.4
Summary: 
License: LGPL-3.0-or-later
Author: Przemysław K. Rekucki
Author-email: prekucki@rcl.pl
Requires-Python: >=3.6,<4.0
Classifier: License :: OSI Approved :: GNU Lesser General Public License v3 or later (LGPLv3+)
Classifier: Programming Language :: Python :: 3
Classifier: Programming Language :: Python :: 3.6
Classifier: Programming Language :: Python :: 3.7
Classifier: Programming Language :: Python :: 3.8
Classifier: Programming Language :: Python :: 3.9
Requires-Dist: aiohttp (>=3.6.2,<4.0.0)
Requires-Dist: certifi (>=2020.6.20,<2021.0.0)
Requires-Dist: python-dateutil (>=2.8.1,<3.0.0)
